bounce/__init__.py
bounce/__main__.py
bounce/asgi.py
bounce/config.py
bounce/controllers.py
bounce/core.py
bounce/wsgi.py
bounce-0.7.0.dist-info/licenses/LICENSE.txt
bounce-0.7.0.dist-info/METADATA
bounce-0.7.0.dist-info/WHEEL
bounce-0.7.0.dist-info/entry_points.txt
bounce-0.7.0.dist-info/top_level.txt
bounce-0.7.0.dist-info/RECORD
