Metadata-Version: 2.4
Name: bounce
Version: 0.7.0
Summary: Search using special commands
Author-email: Jay Marcyes <jay@marcyes.com>
License-Expression: MIT
Project-URL: Repository, https://github.com/Jaymon/bounce
Project-URL: Homepage, http://github.com/Jaymon/bounce
Classifier: Development Status :: 4 - Beta
Classifier: Environment :: Web Environment
Classifier: Intended Audience :: End Users/Desktop
Classifier: Programming Language :: Python :: 3
Classifier: Topic :: Internet :: WWW/HTTP :: HTTP Servers
Requires-Python: >=3.10
License-File: LICENSE.txt
Requires-Dist: datatypes
Requires-Dist: endpoints
Provides-Extra: tests
Requires-Dist: testdata; extra == "tests"
Provides-Extra: asgi
Requires-Dist: daphne; extra == "asgi"
Dynamic: license-file
